<?xml version="1.0" encoding="utf-8" ?>
<dwsync>
<file name="AC_OETags.js" server="107.180.2.25//public_html/" local="131284509453572415" remote="130888944000000000" Dst="0" />
<file name="AC_RunActiveContent.js" server="107.180.2.25//public_html/" local="131284509454853080" remote="130888944000000000" Dst="0" />
<file name="gallery.swf" server="107.180.2.25//public_html/" local="131284509467716544" remote="130888944000000000" Dst="0" />
<file name="group.xml" server="107.180.2.25//public_html/" local="131284509471665749" remote="130888944000000000" Dst="0" />
<file name="loading.swf" server="107.180.2.25//public_html/" local="131284512509445076" remote="130888944000000000" Dst="0" />
<file name="localText.xml" server="107.180.2.25//public_html/" local="131284512509545106" remote="130888944000000000" Dst="0" />
<file name="playerProductInstall.swf" server="107.180.2.25//public_html/" local="131284512509980839" remote="130888944000000000" Dst="0" />
<file name="style.xml" server="107.180.2.25//public_html/" local="131284512517925117" remote="130888944000000000" Dst="0" />
</dwsync>